MANIFEST.in
README.rst
README.txt
setup.py
pymoji/__init__.py
pymoji/utils.py
pymoji.egg-info/PKG-INFO
pymoji.egg-info/SOURCES.txt
pymoji.egg-info/dependency_links.txt
pymoji.egg-info/requires.txt
pymoji.egg-info/top_level.txt
pymoji/resources/__init__.py
pymoji/resources/nature.py
pymoji/resources/objects.py
pymoji/resources/people.py
pymoji/resources/places.py
pymoji/resources/soft_bank.py
pymoji/resources/symbols.py