Metadata-Version: 1.0
Name: pymoji
Version: 0.2.0
Summary: A emoji converter between unicode and ascii text.
Home-page: https://github.com/mapix/pymoji
Author: mapix
Author-email: mapix.me@gmail.com
License: MIT
Platform: UNKNOWN
